{
  "type": "minecraft:chest",
  "pools": [
    {
      "rolls": {
        "min": 9,
        "max": 32
      },
      "entries": [
        {
          "type": "minecraft:item",
          "name": "minecraft:stone_brick_stairs",
          "weight": 1,
          "functions": [
            {
              "function": "set_count",
              "count": {
                "min": 1,
                "max": 1
              }
            }
          ]
        },
        {
          "type": "minecraft:item",
          "name": "minecraft:stone_bricks",
          "weight": 1,
          "functions": [
            {
              "function": "set_count",
              "count": {
                "min": 1,
                "max": 1
              }
            }
          ]
        },
        {
          "type": "minecraft:item",
          "name": "minecraft:mossy_stone_bricks",
          "weight": 1,
          "functions": [
            {
              "function": "set_count",
              "count": {
                "min": 1,
                "max": 1
              }
            }
          ]
        },
        {
          "type": "minecraft:item",
          "name": "minecraft:mossy_stone_brick_stairs",
          "weight": 1,
          "functions": [
            {
              "function": "set_count",
              "count": {
                "min": 1,
                "max": 1
              }
            }
          ]
        },
        {
          "type": "minecraft:item",
          "name": "minecraft:mossy_stone_brick_slab",
          "weight": 1,
          "functions": [
            {
              "function": "set_count",
              "count": {
                "min": 1,
                "max": 1
              }
            }
          ]
        },
        {
          "type": "minecraft:item",
          "name": "minecraft:cracked_stone_bricks",
          "weight": 1,
          "functions": [
            {
              "function": "set_count",
              "count": {
                "min": 1,
                "max": 1
              }
            }
          ]
        },
        {
          "type": "minecraft:item",
          "name": "minecraft:chiseled_stone_bricks",
          "weight": 1,
          "functions": [
            {
              "function": "set_count",
              "count": {
                "min": 1,
                "max": 1
              }
            }
          ]
        },
        {
          "type": "minecraft:item",
          "name": "minecraft:stone_brick_slab",
          "weight": 1,
          "functions": [
            {
              "function": "set_count",
              "count": {
                "min": 1,
                "max": 1
              }
            }
          ]
        },
        {
          "type": "minecraft:item",
          "name": "minecraft:oak_planks",
          "weight": 1,
          "functions": [
            {
              "function": "set_count",
              "count": {
                "min": 1,
                "max": 1
              }
            }
          ]
        },
        {
          "type": "minecraft:item",
          "name": "minecraft:oak_log",
          "weight": 1,
          "functions": [
            {
              "function": "set_count",
              "count": {
                "min": 1,
                "max": 1
              }
            }
          ]
        },
        {
          "type": "minecraft:item",
          "name": "minecraft:stripped_oak_log",
          "weight": 1,
          "functions": [
            {
              "function": "set_count",
              "count": {
                "min": 1,
                "max": 1
              }
            }
          ]
        },
        {
          "type": "minecraft:item",
          "name": "minecraft:oak_wood",
          "weight": 1,
          "functions": [
            {
              "function": "set_count",
              "count": {
                "min": 1,
                "max": 1
              }
            }
          ]
        },
        {
          "type": "minecraft:item",
          "name": "minecraft:stripped_oak_wood",
          "weight": 1,
          "functions": [
            {
              "function": "set_count",
              "count": {
                "min": 1,
                "max": 1
              }
            }
          ]
        }
      ]
    }
  ]
}